engineCrawler/__init__.py
engineCrawler/imageCrawler.py
engineCrawler/requestsTor.py
engineCrawler/selenTor.py
engineCrawler/settings.py
engineCrawler/util.py
engineCrawler-1.3.data/scripts/imageCrawler.py
engineCrawler-1.3.dist-info/LICENSE
engineCrawler-1.3.dist-info/METADATA
engineCrawler-1.3.dist-info/WHEEL
engineCrawler-1.3.dist-info/top_level.txt
engineCrawler-1.3.dist-info/RECORD
